curd/__init__.py
curd/errors.py
curd/session.py
curd-0.0.2.dist-info/DESCRIPTION.rst
curd-0.0.2.dist-info/METADATA
curd-0.0.2.dist-info/RECORD
curd-0.0.2.dist-info/WHEEL
curd-0.0.2.dist-info/metadata.json
curd-0.0.2.dist-info/top_level.txt
