Metadata-Version: 2.0
Name: curd
Version: 0.0.2
Summary: db operations
Home-page: https://github.com/jdxin0/curd
Author: jdxin0
Author-email: jdxin00@gmail.com
License: MIT
Keywords: db operations
Platform: UNKNOWN
Requires-Dist: cassandra-driver (==3.11.0)
Requires-Dist: PyMySQL (==0.7.11)
